determ_package/__init__.py
determ_package/determ.py
determ_package/test.py
determ-0.0.21.dist-info/LICENCE
determ-0.0.21.dist-info/METADATA
determ-0.0.21.dist-info/WHEEL
determ-0.0.21.dist-info/top_level.txt
determ-0.0.21.dist-info/RECORD
