Metadata-Version: 2.1
Name: determ
Version: 0.0.21
Summary: Determ is a simple module which automatically appends the correct determiner to a given string or list element.
Home-page: https://github.com/SunscorchCalvin/determ/issues
Author: Calvin Parsons
Author-email: calvin@sunscorchedstudios.co.uk
License: UNKNOWN
Project-URL: Bug Tracker, https://github.com/SunscorchCalvin/determ/issues
Platform: UNKNOWN
Classifier: Programming Language :: Python :: 3
Classifier: License :: OSI Approved :: MIT License
Classifier: Operating System :: OS Independent
Requires-Python: >=3.6
License-File: LICENCE
